aiohttp_sse_client2/__init__.py
aiohttp_sse_client2/client.py
aiohttp_sse_client2-0.3.0.dist-info/AUTHORS.rst
aiohttp_sse_client2-0.3.0.dist-info/LICENSE
aiohttp_sse_client2-0.3.0.dist-info/METADATA
aiohttp_sse_client2-0.3.0.dist-info/WHEEL
aiohttp_sse_client2-0.3.0.dist-info/top_level.txt
aiohttp_sse_client2-0.3.0.dist-info/RECORD
