Metadata-Version: 2.1
Name: aiohttp-sse-client2
Version: 0.3.0
Summary: A Server-Sent Event python client base on aiohttp
Home-page: https://github.com/JelleZijlstra/aiohttp-sse-client2
Author: Jason Hu
Author-email: awaregit@gmail.com
License: Apache License 2.0
Keywords: aiohttp_sse_client
Classifier: Development Status :: 3 - Alpha
Classifier: Framework :: AsyncIO
Classifier: Intended Audience :: Developers
Classifier: License :: OSI Approved :: Apache Software License
Classifier: Natural Language :: English
Classifier: Programming Language :: Python :: 3
Classifier: Programming Language :: Python :: 3.7
Classifier: Programming Language :: Python :: 3.8
Classifier: Programming Language :: Python :: 3.9
Classifier: Programming Language :: Python :: 3.10
Classifier: Programming Language :: Python :: 3.11
Classifier: Topic :: Internet :: WWW/HTTP
License-File: LICENSE
License-File: AUTHORS.rst
